seedling/__init__.py
seedling-1.0.1.dist-info/LICENSE
seedling-1.0.1.dist-info/METADATA
seedling-1.0.1.dist-info/WHEEL
seedling-1.0.1.dist-info/top_level.txt
seedling-1.0.1.dist-info/RECORD
